{
"meta":{"test_sets":[],"test_metrics":[],"learn_metrics":[{"best_value":"Min","name":"RMSE"}],"launch_mode":"Train","parameters":"","iteration_count":397,"learn_sets":["learn"],"name":"experiment"},
"iterations":[
{"learn":[12.22852356],"iteration":0,"passed_time":0.0756886337,"remaining_time":29.97269895},
{"learn":[10.9310374],"iteration":1,"passed_time":0.08360054141,"remaining_time":16.51110693},
{"learn":[9.946764101],"iteration":2,"passed_time":0.09133415357,"remaining_time":11.99521883},
{"learn":[9.220658886],"iteration":3,"passed_time":0.09885222042,"remaining_time":9.712230657},
{"learn":[8.674773416],"iteration":4,"passed_time":0.1085018298,"remaining_time":8.506543454},
{"learn":[8.280686041],"iteration":5,"passed_time":0.1163193196,"remaining_time":7.580142327},
{"learn":[7.988123298],"iteration":6,"passed_time":0.1243398125,"remaining_time":6.927503838},
{"learn":[7.774276018],"iteration":7,"passed_time":0.132091009,"remaining_time":6.422925311},
{"learn":[7.621706785],"iteration":8,"passed_time":0.1389355204,"remaining_time":5.989664657},
{"learn":[7.493971928],"iteration":9,"passed_time":0.1467231756,"remaining_time":5.678186897},
{"learn":[7.40845081],"iteration":10,"passed_time":0.1541071568,"remaining_time":5.40776023},
{"learn":[7.349431487],"iteration":11,"passed_time":0.1635713875,"remaining_time":5.247915348},
{"learn":[7.29614714],"iteration":12,"passed_time":0.1740142206,"remaining_time":5.140112363},
{"learn":[7.258728093],"iteration":13,"passed_time":0.1832798633,"remaining_time":5.014013404},
{"learn":[7.224968762],"iteration":14,"passed_time":0.1910253097,"remaining_time":4.864777887},
{"learn":[7.202372757],"iteration":15,"passed_time":0.1984583329,"remaining_time":4.725789052},
{"learn":[7.182149448],"iteration":16,"passed_time":0.206290197,"remaining_time":4.611192639},
{"learn":[7.16609575],"iteration":17,"passed_time":0.2149270771,"remaining_time":4.525409013},
{"learn":[7.153643037],"iteration":18,"passed_time":0.222392476,"remaining_time":4.424439785},
{"learn":[7.143469863],"iteration":19,"passed_time":0.2292641539,"remaining_time":4.321629302},
{"learn":[7.129205877],"iteration":20,"passed_time":0.2364385889,"remaining_time":4.23337664},
{"learn":[7.120461659],"iteration":21,"passed_time":0.2433863524,"remaining_time":4.148631007},
{"learn":[7.113718604],"iteration":22,"passed_time":0.2507247077,"remaining_time":4.077001769},
{"learn":[7.106770421],"iteration":23,"passed_time":0.2576283873,"remaining_time":4.003974519},
{"learn":[7.101029599],"iteration":24,"passed_time":0.2649847839,"remaining_time":3.942973585},
{"learn":[7.095589406],"iteration":25,"passed_time":0.2720078409,"remaining_time":3.881342653},
{"learn":[7.089271035],"iteration":26,"passed_time":0.2795418661,"remaining_time":3.830758906},
{"learn":[7.085946025],"iteration":27,"passed_time":0.2864878376,"remaining_time":3.775500431},
{"learn":[7.080012711],"iteration":28,"passed_time":0.2935728538,"remaining_time":3.725338283},
{"learn":[7.075083291],"iteration":29,"passed_time":0.3013287164,"remaining_time":3.686254631},
{"learn":[7.071078775],"iteration":30,"passed_time":0.3083166057,"remaining_time":3.640125086},
{"learn":[7.06870096],"iteration":31,"passed_time":0.3163338065,"remaining_time":3.60818248},
{"learn":[7.064432702],"iteration":32,"passed_time":0.3240320849,"remaining_time":3.574172088},
{"learn":[7.061255825],"iteration":33,"passed_time":0.3313184802,"remaining_time":3.537312009},
{"learn":[7.056785656],"iteration":34,"passed_time":0.3384236638,"remaining_time":3.500267609},
{"learn":[7.054943045],"iteration":35,"passed_time":0.3457155592,"remaining_time":3.466758802},
{"learn":[7.051204192],"iteration":36,"passed_time":0.3529645787,"remaining_time":3.434249954},
{"learn":[7.047981441],"iteration":37,"passed_time":0.360409352,"remaining_time":3.404919931},
{"learn":[7.04552624],"iteration":38,"passed_time":0.3682781759,"remaining_time":3.380604794},
{"learn":[7.043885305],"iteration":39,"passed_time":0.3760632901,"remaining_time":3.356364864},
{"learn":[7.04193576],"iteration":40,"passed_time":0.3834140206,"remaining_time":3.329155886},
{"learn":[7.039813825],"iteration":41,"passed_time":0.3905806635,"remaining_time":3.30133656},
{"learn":[7.037565185],"iteration":42,"passed_time":0.3980097275,"remaining_time":3.276638222},
{"learn":[7.03476655],"iteration":43,"passed_time":0.4058490088,"remaining_time":3.256015911},
{"learn":[7.033749369],"iteration":44,"passed_time":0.4136913731,"remaining_time":3.235985852},
{"learn":[7.031280543],"iteration":45,"passed_time":0.4224399225,"remaining_time":3.223400278},
{"learn":[7.028858726],"iteration":46,"passed_time":0.430091992,"remaining_time":3.202812707},
{"learn":[7.027325203],"iteration":47,"passed_time":0.4375815583,"remaining_time":3.18158258},
{"learn":[7.025988441],"iteration":48,"passed_time":0.4453442961,"remaining_time":3.162853368},
{"learn":[7.02479006],"iteration":49,"passed_time":0.4526503167,"remaining_time":3.141393198},
{"learn":[7.022642026],"iteration":50,"passed_time":0.4603068443,"remaining_time":3.122866042},
{"learn":[7.021605649],"iteration":51,"passed_time":0.4679841223,"remaining_time":3.104894658},
{"learn":[7.020322793],"iteration":52,"passed_time":0.476195703,"remaining_time":3.090779657},
{"learn":[7.018483563],"iteration":53,"passed_time":0.4837281862,"remaining_time":3.072569775},
{"learn":[7.016932997],"iteration":54,"passed_time":0.4911528762,"remaining_time":3.054077885},
{"learn":[7.015857345],"iteration":55,"passed_time":0.4985745661,"remaining_time":3.035962983},
{"learn":[7.01473966],"iteration":56,"passed_time":0.5064603483,"remaining_time":3.020991551},
{"learn":[7.013623374],"iteration":57,"passed_time":0.5145903433,"remaining_time":3.007691834},
{"learn":[7.012644546],"iteration":58,"passed_time":0.5227279645,"remaining_time":2.994611051},
{"learn":[7.011227161],"iteration":59,"passed_time":0.5414672961,"remaining_time":3.041241313},
{"learn":[7.010286897],"iteration":60,"passed_time":0.5547416857,"remaining_time":3.055626334},
{"learn":[7.009116681],"iteration":61,"passed_time":0.5772561345,"remaining_time":3.119045243},
{"learn":[7.008043786],"iteration":62,"passed_time":0.5845271964,"remaining_time":3.098921962},
{"learn":[7.006300116],"iteration":63,"passed_time":0.5920943052,"remaining_time":3.080740682},
{"learn":[7.004992734],"iteration":64,"passed_time":0.6001776324,"remaining_time":3.065522676},
{"learn":[7.004168079],"iteration":65,"passed_time":0.6074612355,"remaining_time":3.046510136},
{"learn":[7.003138036],"iteration":66,"passed_time":0.6159355705,"remaining_time":3.033712511},
{"learn":[7.001876605],"iteration":67,"passed_time":0.6240563573,"remaining_time":3.019331494},
{"learn":[7.001122507],"iteration":68,"passed_time":0.6325125259,"remaining_time":3.00672621},
{"learn":[7.000311296],"iteration":69,"passed_time":0.6404263086,"remaining_time":2.991705756},
{"learn":[6.999023571],"iteration":70,"passed_time":0.6490053546,"remaining_time":2.979940079},
{"learn":[6.997750269],"iteration":71,"passed_time":0.658001409,"remaining_time":2.970145249},
{"learn":[6.996570476],"iteration":72,"passed_time":0.6670767569,"remaining_time":2.960724236},
{"learn":[6.995370211],"iteration":73,"passed_time":0.6765182781,"remaining_time":2.952910862},
{"learn":[6.994275753],"iteration":74,"passed_time":0.6859505911,"remaining_time":2.945014538},
{"learn":[6.993075875],"iteration":75,"passed_time":0.6952598596,"remaining_time":2.936558091},
{"learn":[6.99218562],"iteration":76,"passed_time":0.7036958198,"remaining_time":2.92445016},
{"learn":[6.991229729],"iteration":77,"passed_time":0.7136711026,"remaining_time":2.918731817},
{"learn":[6.990098604],"iteration":78,"passed_time":0.723371296,"remaining_time":2.911798381},
{"learn":[6.988561689],"iteration":79,"passed_time":0.7340370496,"remaining_time":2.908621809},
{"learn":[6.987372465],"iteration":80,"passed_time":0.7434026943,"remaining_time":2.900188289},
{"learn":[6.986296608],"iteration":81,"passed_time":0.7567407101,"remaining_time":2.906991752},
{"learn":[6.984945442],"iteration":82,"passed_time":0.768572404,"remaining_time":2.907611263},
{"learn":[6.983938455],"iteration":83,"passed_time":0.7777336696,"remaining_time":2.897983793},
{"learn":[6.983114513],"iteration":84,"passed_time":0.787740161,"remaining_time":2.891469768},
{"learn":[6.982313096],"iteration":85,"passed_time":0.7966955896,"remaining_time":2.881073585},
{"learn":[6.981189267],"iteration":86,"passed_time":0.8072894257,"remaining_time":2.876548528},
{"learn":[6.980513253],"iteration":87,"passed_time":0.8197425489,"remaining_time":2.878414178},
{"learn":[6.979646247],"iteration":88,"passed_time":0.829277739,"remaining_time":2.869860041},
{"learn":[6.978625308],"iteration":89,"passed_time":0.8387972628,"remaining_time":2.861230663},
{"learn":[6.977943323],"iteration":90,"passed_time":0.8480702806,"remaining_time":2.851752812},
{"learn":[6.977182936],"iteration":91,"passed_time":0.8582878593,"remaining_time":2.845410838},
{"learn":[6.976060655],"iteration":92,"passed_time":0.8689020298,"remaining_time":2.840281904},
{"learn":[6.975084353],"iteration":93,"passed_time":0.8797501211,"remaining_time":2.835790284},
{"learn":[6.974398347],"iteration":94,"passed_time":0.8906562135,"remaining_time":2.831349226},
{"learn":[6.973461428],"iteration":95,"passed_time":0.9007395815,"remaining_time":2.824193896},
{"learn":[6.9727885],"iteration":96,"passed_time":0.9116708834,"remaining_time":2.81960067},
{"learn":[6.972256585],"iteration":97,"passed_time":0.9222830109,"remaining_time":2.813904288},
{"learn":[6.97139798],"iteration":98,"passed_time":0.9309721011,"remaining_time":2.802320062},
{"learn":[6.970969608],"iteration":99,"passed_time":0.9417347326,"remaining_time":2.796952156},
{"learn":[6.969758711],"iteration":100,"passed_time":0.9510153336,"remaining_time":2.787134047},
{"learn":[6.969055817],"iteration":101,"passed_time":0.9597719252,"remaining_time":2.77581096},
{"learn":[6.968122215],"iteration":102,"passed_time":0.9690316937,"remaining_time":2.765973961},
{"learn":[6.967030544],"iteration":103,"passed_time":0.9783455884,"remaining_time":2.756300552},
{"learn":[6.966319173],"iteration":104,"passed_time":0.9872746834,"remaining_time":2.745563881},
{"learn":[6.965660334],"iteration":105,"passed_time":0.9954493463,"remaining_time":2.732790187},
{"learn":[6.965035335],"iteration":106,"passed_time":1.005630716,"remaining_time":2.725541194},
{"learn":[6.964188658],"iteration":107,"passed_time":1.014664854,"remaining_time":2.71516799},
{"learn":[6.963513845],"iteration":108,"passed_time":1.023257942,"remaining_time":2.703654011},
{"learn":[6.963132557],"iteration":109,"passed_time":1.033065095,"remaining_time":2.695360748},
{"learn":[6.962634007],"iteration":110,"passed_time":1.042003356,"remaining_time":2.684801441},
{"learn":[6.961813994],"iteration":111,"passed_time":1.051178955,"remaining_time":2.67487502},
{"learn":[6.961530138],"iteration":112,"passed_time":1.061622455,"remaining_time":2.668148472},
{"learn":[6.961048816],"iteration":113,"passed_time":1.070026706,"remaining_time":2.656294366},
{"learn":[6.960410268],"iteration":114,"passed_time":1.078162452,"remaining_time":2.643841839},
{"learn":[6.959829543],"iteration":115,"passed_time":1.086073527,"remaining_time":2.630919491},
{"learn":[6.959294431],"iteration":116,"passed_time":1.094207314,"remaining_time":2.618615794},
{"learn":[6.958478583],"iteration":117,"passed_time":1.102211807,"remaining_time":2.60607707},
{"learn":[6.95767538],"iteration":118,"passed_time":1.110726311,"remaining_time":2.594806004},
{"learn":[6.957010618],"iteration":119,"passed_time":1.118647844,"remaining_time":2.582212107},
{"learn":[6.95652686],"iteration":120,"passed_time":1.127335767,"remaining_time":2.571443568},
{"learn":[6.955907955],"iteration":121,"passed_time":1.135889105,"remaining_time":2.560405769},
{"learn":[6.955437472],"iteration":122,"passed_time":1.144122644,"remaining_time":2.548695971},
{"learn":[6.954759637],"iteration":123,"passed_time":1.152831067,"remaining_time":2.538087753},
{"learn":[6.954028847],"iteration":124,"passed_time":1.162932894,"remaining_time":2.530541977},
{"learn":[6.953442608],"iteration":125,"passed_time":1.173443311,"remaining_time":2.523834423},
{"learn":[6.953092408],"iteration":126,"passed_time":1.184138149,"remaining_time":2.517459058},
{"learn":[6.952395377],"iteration":127,"passed_time":1.193696131,"remaining_time":2.508627025},
{"learn":[6.951646089],"iteration":128,"passed_time":1.204765893,"remaining_time":2.50292449},
{"learn":[6.950851796],"iteration":129,"passed_time":1.214173497,"remaining_time":2.493725567},
{"learn":[6.950058363],"iteration":130,"passed_time":1.224656539,"remaining_time":2.486707171},
{"learn":[6.949520866],"iteration":131,"passed_time":1.234903577,"remaining_time":2.479162485},
{"learn":[6.948630556],"iteration":132,"passed_time":1.244634063,"remaining_time":2.470551825},
{"learn":[6.948015598],"iteration":133,"passed_time":1.253918373,"remaining_time":2.461048748},
{"learn":[6.947288309],"iteration":134,"passed_time":1.26260188,"remaining_time":2.450382909},
{"learn":[6.946467943],"iteration":135,"passed_time":1.27197365,"remaining_time":2.441067079},
{"learn":[6.946060263],"iteration":136,"passed_time":1.281550924,"remaining_time":2.43214044},
{"learn":[6.945340855],"iteration":137,"passed_time":1.290233514,"remaining_time":2.421525219},
{"learn":[6.944249938],"iteration":138,"passed_time":1.300027625,"remaining_time":2.413000916},
{"learn":[6.94361708],"iteration":139,"passed_time":1.310259912,"remaining_time":2.405262839},
{"learn":[6.943147112],"iteration":140,"passed_time":1.318557787,"remaining_time":2.393977258},
{"learn":[6.94270892],"iteration":141,"passed_time":1.327396629,"remaining_time":2.383705214},
{"learn":[6.942022938],"iteration":142,"passed_time":1.336314057,"remaining_time":2.3735928},
{"learn":[6.941483082],"iteration":143,"passed_time":1.345872455,"remaining_time":2.364623133},
{"learn":[6.941010857],"iteration":144,"passed_time":1.355310518,"remaining_time":2.355436211},
{"learn":[6.940744418],"iteration":145,"passed_time":1.365616016,"remaining_time":2.347737123},
{"learn":[6.93988681],"iteration":146,"passed_time":1.374391983,"remaining_time":2.337401331},
{"learn":[6.939306419],"iteration":147,"passed_time":1.38349733,"remaining_time":2.327640779},
{"learn":[6.938643462],"iteration":148,"passed_time":1.392658722,"remaining_time":2.317982302},
{"learn":[6.938038676],"iteration":149,"passed_time":1.40229308,"remaining_time":2.309109272},
{"learn":[6.937646946],"iteration":150,"passed_time":1.409845814,"remaining_time":2.296834903},
{"learn":[6.937125849],"iteration":151,"passed_time":1.417986519,"remaining_time":2.285570376},
{"learn":[6.936506506],"iteration":152,"passed_time":1.426606733,"remaining_time":2.275111391},
{"learn":[6.936198122],"iteration":153,"passed_time":1.434769562,"remaining_time":2.263954569},
{"learn":[6.935836536],"iteration":154,"passed_time":1.443691615,"remaining_time":2.254021748},
{"learn":[6.935177909],"iteration":155,"passed_time":1.452782421,"remaining_time":2.244362587},
{"learn":[6.934087841],"iteration":156,"passed_time":1.46074783,"remaining_time":2.232990314},
{"learn":[6.933369895],"iteration":157,"passed_time":1.469152998,"remaining_time":2.22232637},
{"learn":[6.933024375],"iteration":158,"passed_time":1.477965131,"remaining_time":2.212300008},
{"learn":[6.932472389],"iteration":159,"passed_time":1.487222274,"remaining_time":2.202947993},
{"learn":[6.93195767],"iteration":160,"passed_time":1.495254059,"remaining_time":2.191800981},
{"learn":[6.931376674],"iteration":161,"passed_time":1.503952607,"remaining_time":2.181659646},
{"learn":[6.930640592],"iteration":162,"passed_time":1.512677322,"remaining_time":2.171573579},
{"learn":[6.929998359],"iteration":163,"passed_time":1.521642751,"remaining_time":2.161846103},
{"learn":[6.929678246],"iteration":164,"passed_time":1.529776247,"remaining_time":2.150958117},
{"learn":[6.929039057],"iteration":165,"passed_time":1.538116121,"remaining_time":2.140390506},
{"learn":[6.928502299],"iteration":166,"passed_time":1.547620103,"remaining_time":2.131452836},
{"learn":[6.928298664],"iteration":167,"passed_time":1.558800951,"remaining_time":2.124794153},
{"learn":[6.927856869],"iteration":168,"passed_time":1.567425748,"remaining_time":2.114633553},
{"learn":[6.927361874],"iteration":169,"passed_time":1.576216965,"remaining_time":2.104713241},
{"learn":[6.926735492],"iteration":170,"passed_time":1.58464305,"remaining_time":2.094323563},
{"learn":[6.926429463],"iteration":171,"passed_time":1.593498685,"remaining_time":2.084518629},
{"learn":[6.925724767],"iteration":172,"passed_time":1.602653285,"remaining_time":2.075111768},
{"learn":[6.925251896],"iteration":173,"passed_time":1.611082911,"remaining_time":2.064778673},
{"learn":[6.92477458],"iteration":174,"passed_time":1.619555497,"remaining_time":2.05452183},
{"learn":[6.924196678],"iteration":175,"passed_time":1.628793306,"remaining_time":2.04524614},
{"learn":[6.923690069],"iteration":176,"passed_time":1.637846111,"remaining_time":2.035740929},
{"learn":[6.922922511],"iteration":177,"passed_time":1.64655891,"remaining_time":2.025822479},
{"learn":[6.922291448],"iteration":178,"passed_time":1.656295937,"remaining_time":2.017164884},
{"learn":[6.921679025],"iteration":179,"passed_time":1.664422266,"remaining_time":2.00655351},
{"learn":[6.921308248],"iteration":180,"passed_time":1.672030209,"remaining_time":1.995350967},
{"learn":[6.920523593],"iteration":181,"passed_time":1.680925344,"remaining_time":1.985708511},
{"learn":[6.920364825],"iteration":182,"passed_time":1.690933585,"remaining_time":1.977375887},
{"learn":[6.919840648],"iteration":183,"passed_time":1.69928721,"remaining_time":1.967109651},
{"learn":[6.919621087],"iteration":184,"passed_time":1.708269056,"remaining_time":1.957583999},
{"learn":[6.919380139],"iteration":185,"passed_time":1.718303381,"remaining_time":1.949258136},
{"learn":[6.918731601],"iteration":186,"passed_time":1.725976784,"remaining_time":1.938262699},
{"learn":[6.918137165],"iteration":187,"passed_time":1.735814688,"remaining_time":1.929708882},
{"learn":[6.91763674],"iteration":188,"passed_time":1.745570841,"remaining_time":1.921051507},
{"learn":[6.917485368],"iteration":189,"passed_time":1.755100697,"remaining_time":1.912136023},
{"learn":[6.917129903],"iteration":190,"passed_time":1.764976936,"remaining_time":1.90358769},
{"learn":[6.916319748],"iteration":191,"passed_time":1.773452313,"remaining_time":1.893529814},
{"learn":[6.915809476],"iteration":192,"passed_time":1.781798647,"remaining_time":1.883351937},
{"learn":[6.915287448],"iteration":193,"passed_time":1.791030914,"remaining_time":1.874119977},
{"learn":[6.91482455],"iteration":194,"passed_time":1.799903966,"remaining_time":1.864515903},
{"learn":[6.914423092],"iteration":195,"passed_time":1.809415363,"remaining_time":1.855573918},
{"learn":[6.914111168],"iteration":196,"passed_time":1.819721652,"remaining_time":1.847433149},
{"learn":[6.913380658],"iteration":197,"passed_time":1.828729247,"remaining_time":1.837965253},
{"learn":[6.913190256],"iteration":198,"passed_time":1.836306815,"remaining_time":1.827079143},
{"learn":[6.91258931],"iteration":199,"passed_time":1.845250243,"remaining_time":1.81757149},
{"learn":[6.912468904],"iteration":200,"passed_time":1.854341133,"remaining_time":1.808213244},
{"learn":[6.911861678],"iteration":201,"passed_time":1.86300518,"remaining_time":1.798445595},
{"learn":[6.911327573],"iteration":202,"passed_time":1.8715376,"remaining_time":1.788563027},
{"learn":[6.910951178],"iteration":203,"passed_time":1.879875058,"remaining_time":1.778509246},
{"learn":[6.910485602],"iteration":204,"passed_time":1.887724256,"remaining_time":1.768014913},
{"learn":[6.910374253],"iteration":205,"passed_time":1.897102943,"remaining_time":1.758964379},
{"learn":[6.910185073],"iteration":206,"passed_time":1.905999286,"remaining_time":1.749467944},
{"learn":[6.91001531],"iteration":207,"passed_time":1.914895547,"remaining_time":1.739977203},
{"learn":[6.90934225],"iteration":208,"passed_time":1.92461874,"remaining_time":1.731235996},
{"learn":[6.908651621],"iteration":209,"passed_time":1.933748881,"remaining_time":1.721957337},
{"learn":[6.90826256],"iteration":210,"passed_time":1.941453952,"remaining_time":1.711423863},
{"learn":[6.907686593],"iteration":211,"passed_time":1.950410714,"remaining_time":1.702009349},
{"learn":[6.907476641],"iteration":212,"passed_time":1.959918069,"remaining_time":1.693074764},
{"learn":[6.907154292],"iteration":213,"passed_time":1.969509552,"remaining_time":1.684206767},
{"learn":[6.906658634],"iteration":214,"passed_time":1.9777933,"remaining_time":1.674225026},
{"learn":[6.906347016],"iteration":215,"passed_time":1.98669402,"remaining_time":1.664776007},
{"learn":[6.906178092],"iteration":216,"passed_time":1.995300025,"remaining_time":1.655087579},
{"learn":[6.905593954],"iteration":217,"passed_time":2.003889697,"remaining_time":1.645395668},
{"learn":[6.905147462],"iteration":218,"passed_time":2.011902272,"remaining_time":1.635244769},
{"learn":[6.904604338],"iteration":219,"passed_time":2.020348066,"remaining_time":1.625461853},
{"learn":[6.904203444],"iteration":220,"passed_time":2.028841152,"remaining_time":1.6157287},
{"learn":[6.903645729],"iteration":221,"passed_time":2.038234173,"remaining_time":1.606716128},
{"learn":[6.903397543],"iteration":222,"passed_time":2.046441045,"remaining_time":1.596774627},
{"learn":[6.903306727],"iteration":223,"passed_time":2.055419558,"remaining_time":1.587444569},
{"learn":[6.902721637],"iteration":224,"passed_time":2.064853705,"remaining_time":1.578465943},
{"learn":[6.902461072],"iteration":225,"passed_time":2.07380255,"remaining_time":1.569116089},
{"learn":[6.902166224],"iteration":226,"passed_time":2.081885502,"remaining_time":1.559121301},
{"learn":[6.901974339],"iteration":227,"passed_time":2.090621259,"remaining_time":1.549627162},
{"learn":[6.901468072],"iteration":228,"passed_time":2.099675023,"remaining_time":1.540372943},
{"learn":[6.901052311],"iteration":229,"passed_time":2.108354196,"remaining_time":1.530848481},
{"learn":[6.900578489],"iteration":230,"passed_time":2.116389689,"remaining_time":1.520868781},
{"learn":[6.900077192],"iteration":231,"passed_time":2.124875067,"remaining_time":1.511225802},
{"learn":[6.899532985],"iteration":232,"passed_time":2.134157919,"remaining_time":1.502154072},
{"learn":[6.898922924],"iteration":233,"passed_time":2.142698714,"remaining_time":1.492563634},
{"learn":[6.898464109],"iteration":234,"passed_time":2.150932671,"remaining_time":1.482770607},
{"learn":[6.898028795],"iteration":235,"passed_time":2.159879974,"remaining_time":1.47347744},
{"learn":[6.897584685],"iteration":236,"passed_time":2.167954885,"remaining_time":1.463598235},
{"learn":[6.897328557],"iteration":237,"passed_time":2.177182902,"remaining_time":1.454504544},
{"learn":[6.896871197],"iteration":238,"passed_time":2.185474817,"remaining_time":1.444790883},
{"learn":[6.896492594],"iteration":239,"passed_time":2.194065363,"remaining_time":1.435284425},
{"learn":[6.896052762],"iteration":240,"passed_time":2.20192402,"remaining_time":1.425311814},
{"learn":[6.895817013],"iteration":241,"passed_time":2.208985702,"remaining_time":1.414846214},
{"learn":[6.895707006],"iteration":242,"passed_time":2.217597248,"remaining_time":1.405390849},
{"learn":[6.894956811],"iteration":243,"passed_time":2.226176335,"remaining_time":1.395922046},
{"learn":[6.894503714],"iteration":244,"passed_time":2.234948927,"remaining_time":1.386580559},
{"learn":[6.89408402],"iteration":245,"passed_time":2.244694247,"remaining_time":1.377840777},
{"learn":[6.893763502],"iteration":246,"passed_time":2.252596988,"remaining_time":1.367973879},
{"learn":[6.89330366],"iteration":247,"passed_time":2.262089135,"remaining_time":1.359077747},
{"learn":[6.892868266],"iteration":248,"passed_time":2.270659556,"remaining_time":1.349628973},
{"learn":[6.892317751],"iteration":249,"passed_time":2.278638673,"remaining_time":1.33983954},
{"learn":[6.892112784],"iteration":250,"passed_time":2.287953067,"remaining_time":1.330841226},
{"learn":[6.891635566],"iteration":251,"passed_time":2.296380943,"remaining_time":1.321330304},
{"learn":[6.891307271],"iteration":252,"passed_time":2.304165265,"remaining_time":1.311461653},
{"learn":[6.890815752],"iteration":253,"passed_time":2.312574183,"remaining_time":1.301961056},
{"learn":[6.890461029],"iteration":254,"passed_time":2.321525902,"remaining_time":1.292771287},
{"learn":[6.890158812],"iteration":255,"passed_time":2.330345912,"remaining_time":1.283510834},
{"learn":[6.889855909],"iteration":256,"passed_time":2.339325133,"remaining_time":1.274340539},
{"learn":[6.889305515],"iteration":257,"passed_time":2.348459065,"remaining_time":1.265255078},
{"learn":[6.88877711],"iteration":258,"passed_time":2.356517435,"remaining_time":1.255596162},
{"learn":[6.888534076],"iteration":259,"passed_time":2.365864037,"remaining_time":1.246628358},
{"learn":[6.888294463],"iteration":260,"passed_time":2.375588231,"remaining_time":1.237854404},
{"learn":[6.887618694],"iteration":261,"passed_time":2.384169235,"remaining_time":1.228484148},
{"learn":[6.887193598],"iteration":262,"passed_time":2.393163289,"remaining_time":1.219330345},
{"learn":[6.886665964],"iteration":263,"passed_time":2.401938256,"remaining_time":1.210067379},
{"learn":[6.886343659],"iteration":264,"passed_time":2.411382485,"remaining_time":1.201141464},
{"learn":[6.886207179],"iteration":265,"passed_time":2.419132015,"remaining_time":1.191377045},
{"learn":[6.88562711],"iteration":266,"passed_time":2.427919523,"remaining_time":1.182133101},
{"learn":[6.885317474],"iteration":267,"passed_time":2.437077163,"remaining_time":1.173070724},
{"learn":[6.885151633],"iteration":268,"passed_time":2.445302619,"remaining_time":1.163564072},
{"learn":[6.884674576],"iteration":269,"passed_time":2.455412446,"remaining_time":1.154953262},
{"learn":[6.883934445],"iteration":270,"passed_time":2.465036721,"remaining_time":1.146105634},
{"learn":[6.883640505],"iteration":271,"passed_time":2.473519848,"remaining_time":1.136727871},
{"learn":[6.883182797],"iteration":272,"passed_time":2.482856826,"remaining_time":1.127744492},
{"learn":[6.882614097],"iteration":273,"passed_time":2.492676647,"remaining_time":1.118975283},
{"learn":[6.882333617],"iteration":274,"passed_time":2.50137332,"remaining_time":1.109700164},
{"learn":[6.881845243],"iteration":275,"passed_time":2.509726944,"remaining_time":1.100278842},
{"learn":[6.881722928],"iteration":276,"passed_time":2.517405265,"remaining_time":1.090572678},
{"learn":[6.881544721],"iteration":277,"passed_time":2.525930434,"remaining_time":1.081243603},
{"learn":[6.881127707],"iteration":278,"passed_time":2.535185452,"remaining_time":1.072228972},
{"learn":[6.880744183],"iteration":279,"passed_time":2.544943729,"remaining_time":1.063422916},
{"learn":[6.880275057],"iteration":280,"passed_time":2.553737155,"remaining_time":1.054211779},
{"learn":[6.880057451],"iteration":281,"passed_time":2.561948526,"remaining_time":1.044766243},
{"learn":[6.879937207],"iteration":282,"passed_time":2.57292487,"remaining_time":1.036443234},
{"learn":[6.879520558],"iteration":283,"passed_time":2.580944238,"remaining_time":1.026924996},
{"learn":[6.879199348],"iteration":284,"passed_time":2.59005892,"remaining_time":1.017847716},
{"learn":[6.878792037],"iteration":285,"passed_time":2.599927533,"remaining_time":1.009062784},
{"learn":[6.878384105],"iteration":286,"passed_time":2.609134634,"remaining_time":1.000016759},
{"learn":[6.878291327],"iteration":287,"passed_time":2.618437027,"remaining_time":0.9910056805},
{"learn":[6.878082601],"iteration":288,"passed_time":2.628345809,"remaining_time":0.982219195},
{"learn":[6.877929953],"iteration":289,"passed_time":2.636721351,"remaining_time":0.972859257},
{"learn":[6.877629922],"iteration":290,"passed_time":2.645099143,"remaining_time":0.9635069043},
{"learn":[6.877423764],"iteration":291,"passed_time":2.653643271,"remaining_time":0.9542210393},
{"learn":[6.877102309],"iteration":292,"passed_time":2.66238882,"remaining_time":0.9450117315},
{"learn":[6.876476353],"iteration":293,"passed_time":2.672102889,"remaining_time":0.9361448897},
{"learn":[6.876213545],"iteration":294,"passed_time":2.680255969,"remaining_time":0.9267325722},
{"learn":[6.875522768],"iteration":295,"passed_time":2.688833056,"remaining_time":0.9174734413},
{"learn":[6.875179878],"iteration":296,"passed_time":2.697780942,"remaining_time":0.9083437515},
{"learn":[6.874670589],"iteration":297,"passed_time":2.706801914,"remaining_time":0.899239562},
{"learn":[6.874238252],"iteration":298,"passed_time":2.715296291,"remaining_time":0.8899633329},
{"learn":[6.873883654],"iteration":299,"passed_time":2.723614582,"remaining_time":0.8806353815},
{"learn":[6.873423326],"iteration":300,"passed_time":2.734147458,"remaining_time":0.8720204517},
{"learn":[6.873105715],"iteration":301,"passed_time":2.743261472,"remaining_time":0.8629464897},
{"learn":[6.872921482],"iteration":302,"passed_time":2.752889581,"remaining_time":0.8540317513},
{"learn":[6.872625944],"iteration":303,"passed_time":2.762739862,"remaining_time":0.8451802867},
{"learn":[6.872133994],"iteration":304,"passed_time":2.772610393,"remaining_time":0.8363283807},
{"learn":[6.871990459],"iteration":305,"passed_time":2.780981142,"remaining_time":0.8270238038},
{"learn":[6.871700209],"iteration":306,"passed_time":2.789788984,"remaining_time":0.8178534481},
{"learn":[6.871276988],"iteration":307,"passed_time":2.798863165,"remaining_time":0.808762408},
{"learn":[6.870862498],"iteration":308,"passed_time":2.807585297,"remaining_time":0.7995712172},
{"learn":[6.870337255],"iteration":309,"passed_time":2.815805336,"remaining_time":0.7902421425},
{"learn":[6.869587987],"iteration":310,"passed_time":2.824672304,"remaining_time":0.7810990938},
{"learn":[6.869110805],"iteration":311,"passed_time":2.833489272,"remaining_time":0.7719441927},
{"learn":[6.868830622],"iteration":312,"passed_time":2.840831418,"remaining_time":0.7623956522},
{"learn":[6.868570061],"iteration":313,"passed_time":2.85068824,"remaining_time":0.7535258723},
{"learn":[6.868143388],"iteration":314,"passed_time":2.859776504,"remaining_time":0.7444497566},
{"learn":[6.867671817],"iteration":315,"passed_time":2.868206589,"remaining_time":0.7352048535},
{"learn":[6.867519311],"iteration":316,"passed_time":2.877219686,"remaining_time":0.7261122235},
{"learn":[6.867271555],"iteration":317,"passed_time":2.887005006,"remaining_time":0.7172119354},
{"learn":[6.866977596],"iteration":318,"passed_time":2.895960976,"remaining_time":0.7081033108},
{"learn":[6.86690943],"iteration":319,"passed_time":2.90554225,"remaining_time":0.699146104},
{"learn":[6.866276732],"iteration":320,"passed_time":2.915099066,"remaining_time":0.6901792181},
{"learn":[6.865979243],"iteration":321,"passed_time":2.922979473,"remaining_time":0.6808182002},
{"learn":[6.865683587],"iteration":322,"passed_time":2.932186323,"remaining_time":0.6717702413},
{"learn":[6.865238954],"iteration":323,"passed_time":2.940270234,"remaining_time":0.6624682936},
{"learn":[6.864724145],"iteration":324,"passed_time":2.948451564,"remaining_time":0.6531954233},
{"learn":[6.86428207],"iteration":325,"passed_time":2.957013234,"remaining_time":0.6440120848},
{"learn":[6.863793519],"iteration":326,"passed_time":2.965454402,"remaining_time":0.6348067528},
{"learn":[6.863348939],"iteration":327,"passed_time":2.974030489,"remaining_time":0.6256344627},
{"learn":[6.862845622],"iteration":328,"passed_time":2.98326409,"remaining_time":0.6166016965},
{"learn":[6.862448023],"iteration":329,"passed_time":2.992258103,"remaining_time":0.6075190693},
{"learn":[6.862034803],"iteration":330,"passed_time":3.001295867,"remaining_time":0.5984457016},
{"learn":[6.861748897],"iteration":331,"passed_time":3.00944957,"remaining_time":0.5891994641},
{"learn":[6.861338022],"iteration":332,"passed_time":3.018745548,"remaining_time":0.5801793245},
{"learn":[6.861061247],"iteration":333,"passed_time":3.027366928,"remaining_time":0.5710302887},
{"learn":[6.860774217],"iteration":334,"passed_time":3.034930828,"remaining_time":0.5616886906},
{"learn":[6.86038229],"iteration":335,"passed_time":3.043501583,"remaining_time":0.552540466},
{"learn":[6.860117381],"iteration":336,"passed_time":3.051938543,"remaining_time":0.5433718475},
{"learn":[6.859685442],"iteration":337,"passed_time":3.060139749,"remaining_time":0.5341664059},
{"learn":[6.859317851],"iteration":338,"passed_time":3.068103283,"remaining_time":0.5249262253},
{"learn":[6.85913553],"iteration":339,"passed_time":3.076945501,"remaining_time":0.5158408634},
{"learn":[6.858769767],"iteration":340,"passed_time":3.087368626,"remaining_time":0.5070165485},
{"learn":[6.85836095],"iteration":341,"passed_time":3.096641852,"remaining_time":0.4979979587},
{"learn":[6.858036679],"iteration":342,"passed_time":3.104665887,"remaining_time":0.4887812184},
{"learn":[6.857877284],"iteration":343,"passed_time":3.113642066,"remaining_time":0.4797181091},
{"learn":[6.85780695],"iteration":344,"passed_time":3.122933294,"remaining_time":0.4707029892},
{"learn":[6.857475443],"iteration":345,"passed_time":3.135031202,"remaining_time":0.4620999748},
{"learn":[6.857212657],"iteration":346,"passed_time":3.143600705,"remaining_time":0.4529684014},
{"learn":[6.856932563],"iteration":347,"passed_time":3.151715492,"remaining_time":0.443776032},
{"learn":[6.856701348],"iteration":348,"passed_time":3.160860133,"remaining_time":0.4347314795},
{"learn":[6.856617464],"iteration":349,"passed_time":3.169759643,"remaining_time":0.4256534378},
{"learn":[6.856238675],"iteration":350,"passed_time":3.178340439,"remaining_time":0.4165346444},
{"learn":[6.855864139],"iteration":351,"passed_time":3.1868454,"remaining_time":0.4074092131},
{"learn":[6.855422166],"iteration":352,"passed_time":3.195742411,"remaining_time":0.3983361645},
{"learn":[6.855036649],"iteration":353,"passed_time":3.205040971,"remaining_time":0.3893128863},
{"learn":[6.854819562],"iteration":354,"passed_time":3.21449291,"remaining_time":0.3803062034},
{"learn":[6.854475082],"iteration":355,"passed_time":3.224841032,"remaining_time":0.3714002312},
{"learn":[6.854214458],"iteration":356,"passed_time":3.233361577,"remaining_time":0.3622814092},
{"learn":[6.853745762],"iteration":357,"passed_time":3.241347611,"remaining_time":0.3531077006},
{"learn":[6.853588631],"iteration":358,"passed_time":3.249589358,"remaining_time":0.3439676758},
{"learn":[6.853243881],"iteration":359,"passed_time":3.258861209,"remaining_time":0.3349385131},
{"learn":[6.852831554],"iteration":360,"passed_time":3.267418546,"remaining_time":0.3258367525},
{"learn":[6.85229971],"iteration":361,"passed_time":3.276513102,"remaining_time":0.3167899408},
{"learn":[6.851782947],"iteration":362,"passed_time":3.284930145,"remaining_time":0.3076794075},
{"learn":[6.851416494],"iteration":363,"passed_time":3.294352415,"remaining_time":0.2986638179},
{"learn":[6.851016824],"iteration":364,"passed_time":3.302518161,"remaining_time":0.2895358388},
{"learn":[6.850719669],"iteration":365,"passed_time":3.310176647,"remaining_time":0.2803701531},
{"learn":[6.850369568],"iteration":366,"passed_time":3.319325454,"remaining_time":0.2713345058},
{"learn":[6.850222293],"iteration":367,"passed_time":3.328222965,"remaining_time":0.2622784401},
{"learn":[6.849913418],"iteration":368,"passed_time":3.336465129,"remaining_time":0.2531735057},
{"learn":[6.849703244],"iteration":369,"passed_time":3.346806127,"remaining_time":0.244226393},
{"learn":[6.849492194],"iteration":370,"passed_time":3.356635907,"remaining_time":0.2352359396},
{"learn":[6.849097916],"iteration":371,"passed_time":3.366265391,"remaining_time":0.2262275128},
{"learn":[6.848875461],"iteration":372,"passed_time":3.375006148,"remaining_time":0.2171585725},
{"learn":[6.848508605],"iteration":373,"passed_time":3.383537234,"remaining_time":0.208078493},
{"learn":[6.848112482],"iteration":374,"passed_time":3.392224574,"remaining_time":0.1990105084},
{"learn":[6.847699862],"iteration":375,"passed_time":3.401954268,"remaining_time":0.190002765},
{"learn":[6.846864748],"iteration":376,"passed_time":3.410287351,"remaining_time":0.1809171009},
{"learn":[6.846360092],"iteration":377,"passed_time":3.419102986,"remaining_time":0.1718596739},
{"learn":[6.846230937],"iteration":378,"passed_time":3.428936348,"remaining_time":0.1628518582},
{"learn":[6.845897931],"iteration":379,"passed_time":3.436278744,"remaining_time":0.1537282596},
{"learn":[6.845587229],"iteration":380,"passed_time":3.444891374,"remaining_time":0.1446673543},
{"learn":[6.845454102],"iteration":381,"passed_time":3.454673028,"remaining_time":0.1356547001},
{"learn":[6.845154527],"iteration":382,"passed_time":3.462472059,"remaining_time":0.1265655583},
{"learn":[6.844800884],"iteration":383,"passed_time":3.470774058,"remaining_time":0.1175001634},
{"learn":[6.844526361],"iteration":384,"passed_time":3.479563317,"remaining_time":0.1084539216},
{"learn":[6.844229559],"iteration":385,"passed_time":3.488541329,"remaining_time":0.09941439021},
{"learn":[6.844060593],"iteration":386,"passed_time":3.497523883,"remaining_time":0.09037529414},
{"learn":[6.843563256],"iteration":387,"passed_time":3.522117873,"remaining_time":0.08169861047},
{"learn":[6.843311796],"iteration":388,"passed_time":3.530698795,"remaining_time":0.07261077212},
{"learn":[6.842998771],"iteration":389,"passed_time":3.540516573,"remaining_time":0.06354773337},
{"learn":[6.842510956],"iteration":390,"passed_time":3.551298246,"remaining_time":0.05449562526},
{"learn":[6.842000466],"iteration":391,"passed_time":3.560693058,"remaining_time":0.0454170033},
{"learn":[6.841600795],"iteration":392,"passed_time":3.570784844,"remaining_time":0.03634386609},
{"learn":[6.841190372],"iteration":393,"passed_time":3.579961818,"remaining_time":0.02725859253},
{"learn":[6.840925377],"iteration":394,"passed_time":3.58919767,"remaining_time":0.01817315276},
{"learn":[6.840720078],"iteration":395,"passed_time":3.599603419,"remaining_time":0.009089907624},
{"learn":[6.840502637],"iteration":396,"passed_time":3.608669517,"remaining_time":0}
]}